Workbook

Sheet Capa
B2: KANVAS QA
B3: Caderno de Testes Manuais — Pre-lancamento SaaS Mainstay
B4: Versao 1.0 — 2026-05-15
B7: Como usar este caderno
B8: 1. | C8: Abra a aba do modulo em teste (01 Auth, 02 Configuracao, ...).
B9: 2. | C9: Execute os passos descritos e compare com o resultado esperado.
B10: 3. | C10: Atualize a coluna Status usando o dropdown (Passou, Falhou, Bloqueado, etc.).
B11: 4. | C11: Registre evidencias e bugs na coluna Observacoes (prefixo BUG: para virar fix depois).
B12: 5. | C12: A aba Resumo consolida o progresso automaticamente.
B13: 6. | C13: Cenarios marcados como Critico precisam passar antes do lancamento.
B16: Legenda de Status
B17: Pendente | C17: Ainda nao executado.
B18: Em andamento | C18: Em execucao ou bloqueado parcialmente.
B19: Passou | C19: Cenario executado e resultado bate com o esperado.
B20: Falhou | C20: Resultado diferente do esperado — abrir bug.
B21: Bloqueado | C21: Nao pode ser testado por dependencia externa.
B22: N/A | C22: Nao se aplica a este ambiente ou versao.
B25: Mainstay / Kanvas — Documento interno de QA. Cores: navy #1F3B61 e cyan #00B3C7.

Sheet Resumo
B1: RESUMO DE EXECUCAO
B4: Modulo | C4: Total | D4: Pendente | E4: Em andamento | F4: Passou | G4: Falhou | H4: Bloqueado | I4: Progresso
B5: 01 Auth & Permissoes | C5: =COUNTA('01 Auth & Permissoes'!I:I)-1 | D5: =COUNTIF('01 Auth & Permissoes'!I:I,"Pendente") | E5: =COUNTIF('01 Auth & Permissoes'!I:I,"Em andamento") | F5: =COUNTIF('01 Auth & Permissoes'!I:I,"Passou") | G5: =COUNTIF('01 Auth & Permissoes'!I:I,"Falhou") | H5: =COUNTIF('01 Auth & Permissoes'!I:I,"Bloqueado") | I5: =IFERROR(F5/C5,0)
B6: 02 Configuracao | C6: =COUNTA('02 Configuracao'!I:I)-1 | D6: =COUNTIF('02 Configuracao'!I:I,"Pendente") | E6: =COUNTIF('02 Configuracao'!I:I,"Em andamento") | F6: =COUNTIF('02 Configuracao'!I:I,"Passou") | G6: =COUNTIF('02 Configuracao'!I:I,"Falhou") | H6: =COUNTIF('02 Configuracao'!I:I,"Bloqueado") | I6: =IFERROR(F6/C6,0)
B7: 03 Marcas & Creators | C7: =COUNTA('03 Marcas & Creators'!I:I)-1 | D7: =COUNTIF('03 Marcas & Creators'!I:I,"Pendente") | E7: =COUNTIF('03 Marcas & Creators'!I:I,"Em andamento") | F7: =COUNTIF('03 Marcas & Creators'!I:I,"Passou") | G7: =COUNTIF('03 Marcas & Creators'!I:I,"Falhou") | H7: =COUNTIF('03 Marcas & Creators'!I:I,"Bloqueado") | I7: =IFERROR(F7/C7,0)
B8: 04 Comercial | C8: =COUNTA('04 Comercial'!I:I)-1 | D8: =COUNTIF('04 Comercial'!I:I,"Pendente") | E8: =COUNTIF('04 Comercial'!I:I,"Em andamento") | F8: =COUNTIF('04 Comercial'!I:I,"Passou") | G8: =COUNTIF('04 Comercial'!I:I,"Falhou") | H8: =COUNTIF('04 Comercial'!I:I,"Bloqueado") | I8: =IFERROR(F8/C8,0)
B9: 05 Operacao de Campanhas | C9: =COUNTA('05 Operacao de Campanhas'!I:I)-1 | D9: =COUNTIF('05 Operacao de Campanhas'!I:I,"Pendente") | E9: =COUNTIF('05 Operacao de Campanhas'!I:I,"Em andamento") | F9: =COUNTIF('05 Operacao de Campanhas'!I:I,"Passou") | G9: =COUNTIF('05 Operacao de Campanhas'!I:I,"Falhou") | H9: =COUNTIF('05 Operacao de Campanhas'!I:I,"Bloqueado") | I9: =IFERROR(F9/C9,0)
B10: 06 Financeiro | C10: =COUNTA('06 Financeiro'!I:I)-1 | D10: =COUNTIF('06 Financeiro'!I:I,"Pendente") | E10: =COUNTIF('06 Financeiro'!I:I,"Em andamento") | F10: =COUNTIF('06 Financeiro'!I:I,"Passou") | G10: =COUNTIF('06 Financeiro'!I:I,"Falhou") | H10: =COUNTIF('06 Financeiro'!I:I,"Bloqueado") | I10: =IFERROR(F10/C10,0)
B11: 07 Portal do Creator | C11: =COUNTA('07 Portal do Creator'!I:I)-1 | D11: =COUNTIF('07 Portal do Creator'!I:I,"Pendente") | E11: =COUNTIF('07 Portal do Creator'!I:I,"Em andamento") | F11: =COUNTIF('07 Portal do Creator'!I:I,"Passou") | G11: =COUNTIF('07 Portal do Creator'!I:I,"Falhou") | H11: =COUNTIF('07 Portal do Creator'!I:I,"Bloqueado") | I11: =IFERROR(F11/C11,0)
B12: 08 Sistema & Regressao | C12: =COUNTA('08 Sistema & Regressao'!I:I)-1 | D12: =COUNTIF('08 Sistema & Regressao'!I:I,"Pendente") | E12: =COUNTIF('08 Sistema & Regressao'!I:I,"Em andamento") | F12: =COUNTIF('08 Sistema & Regressao'!I:I,"Passou") | G12: =COUNTIF('08 Sistema & Regressao'!I:I,"Falhou") | H12: =COUNTIF('08 Sistema & Regressao'!I:I,"Bloqueado") | I12: =IFERROR(F12/C12,0)
B13: TOTAL GERAL | C13: =SUM(C5:C12) | D13: =SUM(D5:D12) | E13: =SUM(E5:E12) | F13: =SUM(F5:F12) | G13: =SUM(G5:G12) | H13: =SUM(H5:H12) | I13: =IFERROR(F13/C13,0)
B16: Cenarios marcados como Critico devem passar antes do lancamento.

Sheet 01 Auth & Permissoes
A1: 01 AUTH & PERMISSOES
A3: ID | B3: Submodulo | C3: Cenario | D3: Tipo | E3: Rota | F3: Pre-requisitos | G3: Passos | H3: Resultado esperado | I3: Status | J3: Observacoes
A4: A01 | B4: Login | C4: Login inicial via IdM | D4: Happy | E4: / | F4: Usuario cadastrado no IdM com acesso ao contrato Kanvas | G4: 1) Acessar / 2) Ser redirecionado ao IdM 3) Autenticar 4) Voltar em /callback | H4: Redireciona para Dashboard sem flash de pagina autenticada | I4: Pendente
A5: A02 | B5: Login | C5: Logout limpa sessao | D5: Happy | E5: / | F5: Usuario logado | G5: 1) Clicar em sair na navbar 2) Tentar voltar ao app | H5: Redireciona para IdM e exige novo login | I5: Pendente
A6: A03 | B6: Login | C6: Refresh token automatico | D6: Happy | E6: / | F6: Usuario logado e accessToken proximo de expirar | G6: 1) Aguardar accessToken expirar 2) Disparar requisicao autenticada | H6: Token e renovado sem expor erro 401 ao usuario | I6: Pendente
A7: A04 | B7: Login | C7: Usuario sem acesso ao contrato | D7: Edge | E7: / | F7: Usuario IdM sem vinculo no contrato Kanvas | G7: 1) Tentar logar | H7: Mensagem clara de acesso negado | I7: Pendente
A8: A05 | B8: Login | C8: Multi-contrato (seletor) | D8: Edge | E8: / | F8: Usuario com acesso a 2+ contratos | G8: 1) Logar 2) Selecionar contrato A 3) Logout 4) Logar contrato B | H8: Cada login isola dados do contrato correto | I8: Pendente
A9: A06 | B9: Permissoes | C9: Usuario nao-root nao ve /usuarios | D9: Edge | E9: /usuarios | F9: Usuario logado sem claim root=true | G9: 1) Acessar /usuarios diretamente | H9: Retorna 403 ou esconde menu | I9: Pendente
A10: A07 | B10: Permissoes | C10: Endpoint sem permission retorna 403 | D10: Edge | E10: - | F10: Usuario com role limitado | G10: 1) Acessar acao sem permission claim correspondente | H10: Backend retorna 403 Forbidden | I10: Pendente

Sheet 02 Configuracao
A1: 02 CONFIGURACAO
A3: ID | B3: Submodulo | C3: Cenario | D3: Tipo | E3: Rota | F3: Pre-requisitos | G3: Passos | H3: Resultado esperado | I3: Status | J3: Observacoes
A4: C01 | B4: Pipeline | C4: Cadastrar estagios completos | D4: Happy | E4: /configuracao/pipeline-comercial | F4: Login root | G4: 1) Criar Lead/Qualif/Proposta/Negociacao/Fechado-Ganho/Fechado-Perda 2) Definir FinalBehavior | H4: Estagios listados na ordem e com cores | I4: Pendente
A5: C02 | B5: Pipeline | C5: Estagio sem FinalBehavior | D5: Edge | E5: /configuracao/pipeline-comercial | F5: - | G5: 1) Tentar salvar estagio sem FinalBehavior | H5: Validacao impede ou assume EmAndamento | I5: Pendente
A6: C03 | B6: Origens | C6: CRUD origem oportunidade | D6: Happy | E6: /configuracao/origens-oportunidade | F6: - | G6: 1) Criar Indicacao 2) Criar LinkedIn 3) Editar 4) Excluir | H6: Lista atualiza apos cada operacao | I6: Pendente
A7: C04 | B7: Tags | C7: CRUD de tags | D7: Happy | E7: /configuracao/tags-oportunidade | F7: - | G7: 1) Criar 3 tags 2) Editar 3) Excluir uma usada | H7: Tag em uso bloqueia exclusao ou alerta | I7: Pendente
A8: C05 | B8: Plataformas | C8: Cadastrar redes sociais | D8: Happy | E8: /configuracao/plataformas | F8: - | G8: 1) Cadastrar Instagram TikTok YouTube | H8: Listadas e usaveis em creator | I8: Pendente
A9: C06 | B9: Tipos entrega | C9: CRUD tipos de entrega | D9: Happy | E9: /configuracao/tipos-entrega | F9: - | G9: 1) Cadastrar Post Story Reel Video | H9: Aparecem ao criar Deliverable | I9: Pendente
A10: C07 | B10: Status creator | C10: CRUD status de creator | D10: Happy | E10: /configuracao/status-creators | F10: - | G10: 1) Cadastrar Convidado Confirmado Recusado Substituido | H10: Aparecem em campanha | I10: Pendente
A11: C08 | B11: Templates | C11: Criar template de proposta | D11: Happy | E11: /configuracao/templates-proposta | F11: - | G11: 1) Criar template com blocos | H11: Selecionavel ao gerar proposta | I11: Pendente
A12: C09 | B12: Templates | C12: Editor de template | D12: Happy | E12: /configuracao/template-proposta | F12: - | G12: 1) Editar conteudo 2) Salvar 3) Visualizar preview | H12: Mudancas persistem e preview renderiza | I12: Pendente
A13: C10 | B13: Templates | C13: Templates de documento de campanha | D13: Happy | E13: /configuracao/templates-documento | F13: - | G13: 1) Cadastrar Briefing e Contrato | H13: Selecionavel em documento de campanha | I13: Pendente
A14: C11 | B14: Blocos | C14: CRUD blocos de proposta | D14: Happy | E14: /configuracao/blocos-proposta | F14: - | G14: 1) Criar apresentacao 2) Criar escopo | H14: Reutilizavel em templates | I14: Pendente
A15: C12 | B15: Financeiro | C15: Conta bancaria | D15: Happy | E15: /configuracao/contas-financeiras | F15: - | G15: 1) Cadastrar conta operacional | H15: Aparece em lancamentos financeiros | I15: Pendente
... A20: C17 | B20: Agencia | C20: Dados da agencia | D20: Happy | E20: /configuracao | F20: - | G20: 1) Editar logo dados fiscais e-mail padrao | H20: Persiste e reflete em propostas | I20: Pendente

Sheet 03 Marcas & Creators
A1: 03 MARCAS & CREATORS
A3: ID | B3: Submodulo | C3: Cenario | D3: Tipo | E3: Rota | F3: Pre-requisitos | G3: Passos | H3: Resultado esperado | I3: Status | J3: Observacoes
A4: M01 | B4: Marcas | C4: CRUD de marca | D4: Happy | E4: /marcas | F4: - | G4: 1) Criar ACME 2) Editar contatos 3) Listar com filtro | H4: Marca persiste e filtros funcionam | I4: Pendente
A5: M02 | B5: Marcas | C5: Marca com multiplos contatos | D5: Happy | E5: /marcas | F5: - | G5: 1) Adicionar 3 contatos com papeis distintos | H5: Lista de contatos correta | I5: Pendente
A6: M03 | B6: Marcas | C6: Excluir marca com oportunidade | D6: Edge | E6: /marcas | F6: Marca com oportunidade vinculada | G6: 1) Tentar excluir | H6: Bloqueia ou alerta dependencias | I6: Pendente
A7: CR01 | B7: Creators | C7: Cadastrar creator | D7: Happy | E7: /creators | F7: - | G7: 1) Criar creator com handles e metricas | H7: Persiste e busca funciona | I7: Pendente
A8: CR02 | B8: Creators | C8: Creator 360 (abas) | D8: Happy | E8: /creators/{id} | F8: Creator com historico | G8: 1) Abrir detalhe 2) Navegar abas Campanhas/Financeiro/Historico | H8: Cards de metricas no header e tabs com contadores | I8: Pendente
A9: CR03 | B9: Creators | C9: Dropdown de plataforma usa SearchableSelect | D9: Happy | E9: /creators | F9: Plataformas cadastradas | G9: 1) Abrir form 2) Selecionar plataforma | H9: Dropdown com busca e sentinel para vazio | I9: Pendente
A10: CR04 | B10: Creators | C10: Creator sem handle social | D10: Edge | E10: /creators | F10: - | G10: 1) Criar creator sem handle | H10: Validacao requer pelo menos 1 ou permite vazio | I10: Pendente
A11: CR05 | B11: Creators | C11: Acao em massa | D11: Happy | E11: /creators | F11: - | G11: 1) Selecionar varios 2) Acao em massa | H11: Funciona se feature implementada | I11: Pendente

Sheet 04 Comercial
A1: 04 COMERCIAL
A3: ID | B3: Submodulo | C3: Cenario | D3: Tipo | E3: Rota | F3: Pre-requisitos | G3: Passos | H3: Resultado esperado | I3: Status | J3: Observacoes
A4: O01 | B4: Oportunidades | C4: Criar oportunidade | D4: Happy | E4: /comercial/oportunidades | F4: Marca ACME e origens cadastradas | G4: 1) Marca 2) Origem 3) Responsavel 4) Valor 5) Tags | H4: Lista atualiza com novo card | I4: Pendente
A5: O02 | B5: Oportunidades | C5: Detalhe da oportunidade | D5: Happy | E5: /comercial/oportunidades/{id} | F5: Oportunidade criada | G5: 1) Abrir 2) Conferir follow-up/comentarios/historico/proposta | H5: Cards de metricas no header | I5: Pendente
A6: O03 | B6: Oportunidades | C6: Comentario na oportunidade | D6: Happy | E6: /comercial/oportunidades/{id} | F6: - | G6: 1) Adicionar comentario | H6: Aparece com autor e timestamp | I6: Pendente
A7: O04 | B7: Oportunidades | C7: Listar com filtros | D7: Happy | E7: /comercial/oportunidades | F7: Varias oportunidades | G7: 1) Filtrar por estagio 2) Responsavel 3) Tag | H7: Resultados coerentes | I7: Pendente
A8: O05 | B8: Oportunidades | C8: Busca textual | D8: Happy | E8: /comercial/oportunidades | F8: - | G8: 1) Buscar nome da marca | H8: Encontra rapidamente | I8: Pendente
A9: O06 | B9: Pipeline | C9: Arrastar oportunidade no kanban | D9: Happy | E9: /comercial/pipeline | F9: Oportunidade existente | G9: 1) Arrastar de Lead para Qualificacao | H9: Gera entrada em historico de estagio | I9: Pendente
A10: O07 | B10: Pipeline | C10: Mover para Sucesso | D10: Happy | E10: /comercial/pipeline | F10: Oportunidade com proposta aprovada | G10: 1) Mover para Fechado-Ganho | H10: Dispara opportunity_won | I10: Pendente
A11: O08 | B11: Pipeline | C11: Mover para Perda | D11: Happy | E11: /comercial/pipeline | F11: - | G11: 1) Mover para Fechado-Perda | H11: Dispara opportunity_lost com motivo opcional | I11: Pendente
A12: O09 | B12: Pipeline | C12: Reordenar dentro do estagio | D12: Edge | E12: /comercial/pipeline | F12: Multiplas oportunidades no mesmo estagio | G12: 1) Arrastar dentro da coluna | H12: Ordem persiste apos refresh | I12: Pendente
A13: F01 | B13: Follow-ups | C13: Criar follow-up futuro | D13: Happy | E13: /comercial/followups | F13: Oportunidade existente | G13: 1) Criar com data futura | H13: Aparece com cor neutra | I13: Pendente
A14: F02 | B14: Follow-ups | C14: Follow-up vencido | D14: Edge | E14: /comercial/followups | F14: - | G14: 1) Criar com data passada | H14: Destaque visual e dispara follow_up_overdue | I14: Pendente
A15: F03 | B15: Follow-ups | C15: Concluir follow-up | D15: Happy | E15: /comercial/followups | F15: - | G15: 1) Marcar como concluido | H15: Some da lista de pendentes | I15: Pendente
... A27: P12 | B27: Propostas | C27: Conversao em campanha | D27: Critico | E27: - | F27: Proposta aprovada | G27: 1) Aprovacao 2) Conferir lista de campanhas | H27: Campanha criada com dados herdados | I27: Pendente

Sheet 05 Operacao de Campanhas
A1: 05 OPERACAO DE CAMPANHAS
A3: ID | B3: Submodulo | C3: Cenario | D3: Tipo | E3: Rota | F3: Pre-requisitos | G3: Passos | H3: Resultado esperado | I3: Status | J3: Observacoes
A4: CP01 | B4: Campanhas | C4: Listar campanhas | D4: Happy | E4: /campanhas | F4: Pelo menos 1 campanha | G4: 1) Abrir lista | H4: Filtros e busca funcionando | I4: Pendente
A5: CP02 | B5: Campanhas | C5: Detalhe da campanha | D5: Happy | E5: /campanhas/{id} | F5: - | G5: 1) Conferir abas e metricas no header | H5: Cards e abas com contadores | I5: Pendente
A6: CP03 | B6: Campanhas | C6: Adicionar creators | D6: Happy | E6: /campanhas/{id} | F6: Creators cadastrados | G6: 1) Adicionar 2-3 creators 2) Definir valor combinado | H6: Aparecem com status Convidado | I6: Pendente
A7: CP04 | B7: Campanhas | C7: Trocar status do creator | D7: Happy | E7: /campanhas/{id} | F7: Creator na campanha | G7: 1) Convidado -> Confirmado | H7: Status atualiza com auditoria | I7: Pendente
A8: CP05 | B8: Campanhas | C8: Substituir creator | D8: Edge | E8: /campanhas/{id} | F8: - | G8: 1) Marcar Substituido 2) Adicionar substituto | H8: Historico mantem ambos | I8: Pendente
A9: CP06 | B9: Campanhas | C9: Subir documento via template | D9: Happy | E9: /campanhas/{id} | F9: Template cadastrado | G9: 1) Subir Briefing 2) Subir Contrato | H9: Lista atualiza com versionamento | I9: Pendente
A10: CP07 | B10: Campanhas | C10: Excluir campanha em andamento | D10: Edge | E10: /campanhas/{id} | F10: Campanha com deliverables | G10: 1) Tentar excluir | H10: Bloqueia ou alerta | I10: Pendente
A11: D01 | B11: Deliverables | C11: Criar deliverable | D11: Happy | E11: /campanhas/{id} | F11: Creator na campanha | G11: 1) Tipo data valor | H11: Aparece na lista da campanha | I11: Pendente
A12: D02 | B12: Deliverables | C12: Enviar para aprovacao | D12: Happy | E12: /campanhas/{id} | F12: Deliverable criado | G12: 1) Anexar conteudo 2) Enviar | H12: Gera /d/{token} + dispara deliverable_pending_approval | I12: Pendente
A13: D03 | B13: Deliverables | C13: Link publico | D13: Happy | E13: /d/{token} | F13: - | G13: 1) Abrir em aba anonima | H13: Renderiza sem auth com conteudo | I13: Pendente
A14: D04 | B14: Deliverables | C14: Aprovar via link publico | D14: Happy | E14: /d/{token} | F14: - | G14: 1) Aprovar | H14: Dispara deliverable_approved + notificacao | I14: Pendente
A15: D05 | B15: Deliverables | C15: Recusar via link publico | D15: Edge | E15: /d/{token} | F15: - | G15: 1) Recusar com motivo | H15: Status volta para revisao | I15: Pendente
... A18: D08 | B18: Operacao | C18: Fila de aprovacoes operacionais | D18: Happy | E18: /operacao/aprovacoes | F18: Deliverables aguardando | G18: 1) Conferir fila | H18: Mostra pendentes da marca e prazos | I18: Pendente

Sheet 06 Financeiro
A1: 06 FINANCEIRO
A3: ID | B3: Submodulo | C3: Cenario | D3: Tipo | E3: Rota | F3: Pre-requisitos | G3: Passos | H3: Resultado esperado | I3: Status | J3: Observacoes
A4: FN01 | B4: Receber | C4: Receivables gerados automaticamente | D4: Critico | E4: /financeiro/receber | F4: Proposta aprovada | G4: 1) Conferir lancamentos criados | H4: Valor e parcelamento batem com proposta | I4: Pendente
A5: FN02 | B5: Receber | C5: Lancamento manual a receber | D5: Happy | E5: /financeiro/receber | F5: - | G5: 1) Criar lancamento manual | H5: Persiste com vinculo opcional | I5: Pendente
A6: FN03 | B6: Receber | C6: Baixar pagamento | D6: Happy | E6: /financeiro/receber | F6: - | G6: 1) Marcar como recebido 2) Informar conta | H6: Status Realizado | I6: Pendente
A7: FN04 | B7: Receber | C7: Vencido dispara evento | D7: Edge | E7: /financeiro/receber | F7: Lancamento vencido | G7: 1) Aguardar trigger | H7: Dispara financial_entry_overdue | I7: Pendente
A8: FN05 | B8: Pagar | C8: Despesa avulsa | D8: Happy | E8: /financeiro/pagar | F8: - | G8: 1) Criar despesa | H8: Persiste com subcategoria | I8: Pendente
A9: FN06 | B9: Pagar | C9: Vinculo a marca/campanha | D9: Happy | E9: /financeiro/pagar | F9: - | G9: 1) Vincular a campanha | H9: Aparece em metricas da campanha | I9: Pendente
A10: FN07 | B10: Repasses | C10: Repasses gerados por deliverable | D10: Critico | E10: /financeiro/repasses-creators | F10: Deliverables com valor | G10: 1) Conferir saidas por creator | H10: Bate com somatorio dos deliverables | I10: Pendente
A11: FN08 | B11: Repasses | C11: Aprovar repasse | D11: Happy | E11: /financeiro/repasses-creators | F11: - | G11: 1) Aprovar 2) Definir data | H11: Status segue para pagar | I11: Pendente
A12: FN09 | B12: Repasses | C12: Creator sem dados bancarios | D12: Edge | E12: /financeiro/repasses-creators | F12: Creator sem dados bancarios | G12: 1) Tentar pagar | H12: Bloqueia ou alerta cadastro | I12: Pendente
A13: FN10 | B13: CashFlow | C13: Grafico Nivo | D13: Happy | E13: /financeiro/fluxo-caixa | F13: Lancamentos diversos | G13: 1) Filtrar mes/semana/dia | H13: Grafico sem perder labels do inicio | I13: Pendente
A14: FN11 | B14: CashFlow | C14: Projetado vs realizado | D14: Happy | E14: /financeiro/fluxo-caixa | F14: - | G14: 1) Comparar linhas | H14: Diferenca clara entre projetado e realizado | I14: Pendente
A15: FN12 | B15: Aging | C15: Distribuicao por faixa | D15: Happy | E15: /financeiro/aging | F15: Vencidos em faixas diferentes | G15: 1) Conferir faixas | H15: Faixas batem com somatorios | I15: Pendente
A16: FN13 | B16: Aging | C16: Drill-down em faixa | D16: Happy | E16: /financeiro/aging | F16: - | G16: 1) Clicar em faixa 2) Ver lancamentos | H16: Lista filtrada abre | I16: Pendente

Sheet 07 Portal do Creator
A1: 07 PORTAL DO CREATOR
A3: ID | B3: Submodulo | C3: Cenario | D3: Tipo | E3: Rota | F3: Pre-requisitos | G3: Passos | H3: Resultado esperado | I3: Status | J3: Observacoes
A4: PT01 | B4: Acesso | C4: Acessar portal por token | D4: Happy | E4: /portal/{token} | F4: Creator com token gerado | G4: 1) Abrir link | H4: Sem auth, mostra Dashboard do creator | I4: Pendente
A5: PT02 | B5: Acesso | C5: Listar campanhas do creator | D5: Happy | E5: /portal/{token}/campanhas | F5: - | G5: 1) Abrir aba | H5: Apenas campanhas dele | I5: Pendente
A6: PT03 | B6: Documentos | C6: Contratos para assinar | D6: Happy | E6: /portal/{token}/contratos | F6: - | G6: 1) Abrir contratos | H6: Lista contratos atribuidos | I6: Pendente
A7: PT04 | B7: Pagamentos | C7: Pagamentos do creator | D7: Happy | E7: /portal/{token}/pagamentos | F7: - | G7: 1) Abrir aba | H7: Pagamentos do creator | I7: Pendente
A8: PT05 | B8: Perfil | C8: Editar perfil | D8: Happy | E8: /portal/{token}/perfil | F8: - | G8: 1) Editar dados bancarios e contato | H8: Persiste e reflete no Kanvas | I8: Pendente
A9: PT06 | B9: Acesso | C9: Token invalido | D9: Edge | E9: /portal/{token} | F9: Token errado | G9: 1) Acessar com token adulterado | H9: Mensagem clara, sem expor dados | I9: Pendente

Sheet 08 Sistema & Regressao
A1: 08 SISTEMA & REGRESSAO
A3: ID | B3: Submodulo | C3: Cenario | D3: Tipo | E3: Rota | F3: Pre-requisitos | G3: Passos | H3: Resultado esperado | I3: Status | J3: Observacoes
A4: U01 | B4: Usuarios | C4: Listar usuarios do contrato | D4: Happy | E4: /usuarios | F4: Login root | G4: 1) Abrir tela | H4: Lista via IdM (IntegrationSecret) | I4: Pendente
A5: U02 | B5: Usuarios | C5: Criar usuario | D5: Happy | E5: /usuarios | F5: - | G5: 1) Criar e atribuir papel | H5: Operacao atomica no IdM | I5: Pendente
A6: U03 | B6: Usuarios | C6: Alterar papel | D6: Happy | E6: /usuarios | F6: - | G6: 1) Trocar papel | H6: Permissoes mudam na proxima sessao | I6: Pendente
A7: U04 | B7: Usuarios | C7: Desativar/reativar usuario | D7: Happy | E7: /usuarios | F7: - | G7: 1) Desativar 2) Reativar | H7: Acesso global muda | I7: Pendente
A8: N01 | B8: Notificacoes | C8: Badge por polling 60s | D8: Happy | E8: - | F8: Usuario logado | G8: 1) Disparar evento via outro usuario 2) Aguardar 60s | H8: Badge sem reload | I8: Pendente
A9: N02 | B9: Notificacoes | C9: Marcar como lida | D9: Happy | E9: - | F9: Notificacoes pendentes | G9: 1) Clicar 2) Marcar lida | H9: Badge decrementa | I9: Pendente
A10: N03 | B10: Notificacoes | C10: Navegar para entidade | D10: Happy | E10: - | F10: Notif de proposta aprovada | G10: 1) Clicar item | H10: Vai direto para proposta | I10: Pendente
A11: AU01 | B11: Automacoes | C11: Vincular evento a pipeline | D11: Happy | E11: /configuracao/integracoes | F11: Pipeline pronto no IntegrationPlataform | G11: 1) Configurar proposal_sent -> pipeline | H11: Persistencia ok | I11: Pendente
A12: AU02 | B12: Automacoes | C12: Disparo real proposta enviada | D12: Critico | E12: - | F12: Automacao configurada | G12: 1) Enviar proposta | H12: Pipeline executa com payload Mustache interpolado | I12: Pendente
A13: AU03 | B13: Automacoes | C13: Falha na execucao | D13: Edge | E13: - | F13: Conector com credencial invalida | G13: 1) Disparar evento | H13: Log no Kanvas e retry conforme politica | I13: Pendente
A14: AU04 | B14: Automacoes | C14: Payload com variavel ausente | D14: Edge | E14: - | F14: Template com variavel inexistente | G14: 1) Disparar | H14: Nao quebra pipeline; loga warning | I14: Pendente
A15: AD01 | B15: Auditoria | C15: Listar alteracoes | D15: Happy | E15: - | F15: Entidade alterada | G15: 1) Filtrar por entidade | H15: auditentries + auditpropertychanges legivel | I15: Pendente
... A29: RG05 | B29: Regressao | C29: getById dos services antigos | D29: Edge | E29: - | F29: - | G29: 1) Editar campaignDocument 2) campaignDocumentTemplate 3) creatorPayment | H29: Sem 404 (ver project_creator_service_route_bug) | I29: Pendente
